pgsheets/__init__.py
pgsheets/exceptions.py
pgsheets/models.py
pgsheets/token.py
pgsheets-0.0.1.dist-info/DESCRIPTION.rst
pgsheets-0.0.1.dist-info/METADATA
pgsheets-0.0.1.dist-info/metadata.json
pgsheets-0.0.1.dist-info/RECORD
pgsheets-0.0.1.dist-info/top_level.txt
pgsheets-0.0.1.dist-info/WHEEL
