Metadata-Version: 2.0
Name: pgsheets
Version: 0.0.1
Summary: Manipulate Google Sheets Using Pandas DataFrames
Home-page: https://github.com/henrystokeley/pgsheets
Author: Henry Stokeley
Author-email: henrystokeley@gmail.com
License: MIT
Keywords: pandas google sheets spreadsheets dataframe
Platform: UNKNOWN
Classifier: Development Status :: 3 - Alpha
Classifier: License :: OSI Approved :: MIT License
Classifier: Programming Language :: Python :: 3.4
Classifier: Topic :: Scientific/Engineering
Classifier: Topic :: Office/Business :: Financial :: Spreadsheet
Requires-Dist: pandas (>=0.14.0)
Requires-Dist: requests (>=2.0.0)
